{
    "shop": [
        {
            "sid": 1,
            "Src": "../img/list/0.jpg",
            "sname": "商品1",
            "des": "商品描述",
            "price": "￥30"
        },
        {
            "sid": 2,
            "Src": "../img/list/1.jpg",
            "sname": "商品2",
            "des": "商品描述",
            "price": "￥12"
        },
        {
            "sid": 3,
            "Src": "../img/list/2.jpg",
            "sname": "商品3",
            "des": "商品描述",
            "price": "￥20"
        },
        {
            "sid": 4,
            "Src": "../img/list/3.jpg",
            "sname": "商品4",
            "des": "商品描述",
            "price": "￥13"
        },
        {
            "sid": 5,
            "Src": "../img/list/4.jpg",
            "sname": "商品5",
            "des": "商品描述",
            "price": "￥40"
        },
        {
            "sid": 6,
            "Src": "../img/list/5.jpg",
            "sname": "商品6",
            "des": "商品描述",
            "price": "￥11"
        },
        {
            "sid": 7,
            "Src": "../img/list/6.jpg",
            "sname": "商品7",
            "des": "商品描述",
            "price": "￥22"
        },
        {
            "sid": 8,
            "Src": "../img/list/7.jpg",
            "sname": "商品8",
            "des": "商品描述",
            "price": "￥23"
        },
        {
            "sid": 9,
            "Src": "../img/list/8.jpg",
            "sname": "商品9",
            "des": "商品描述",
            "price": "￥31"
        },
        {
            "sid": 10,
            "Src": "../img/list/9.jpg",
            "sname": "商品10",
            "des": "商品描述",
            "price": "￥8"
        },
        {
            "sid": 11,
            "Src": "../img/list/10.jpg",
            "sname": "商品11",
            "des": "商品描述",
            "price": "￥24"
        },
        {
            "sid": 12,
            "Src": "../img/list/11.jpg",
            "sname": "商品12",
            "des": "商品描述",
            "price": "￥13"
        },
        {
            "sid": 13,
            "Src": "../img/list/12.jpg",
            "sname": "商品13",
            "des": "商品描述",
            "price": "￥18"
        },
        {
            "sid": 14,
            "Src": "../img/list/13.jpg",
            "sname": "商品14",
            "des": "商品描述",
            "price": "￥4"
        },
        {
            "sid": 15,
            "Src": "../img/list/14.jpg",
            "sname": "商品15",
            "des": "商品描述",
            "price": "￥20"
        },
        {
            "sid": 16,
            "Src": "../img/list/15.jpg",
            "sname": "商品16",
            "des": "商品描述",
            "price": "￥30"
        },
        {
            "sid": 17,
            "Src": "../img/list/16.jpg",
            "sname": "商品17",
            "des": "商品描述",
            "price": "￥7"
        },
        {
            "sid": 18,
            "Src": "../img/list/17.jpg",
            "sname": "商品18",
            "des": "商品描述",
            "price": "￥32"
        },
        {
            "sid": 19,
            "Src": "../img/list/18.jpg",
            "sname": "商品19",
            "des": "商品描述",
            "price": "￥9"
        },
        {
            "sid": 20,
            "Src": "../img/list/19.jpg",
            "sname": "商品20",
            "des": "商品描述",
            "price": "￥15"
        },
        {
            "sid": 21,
            "Src": "../img/list/20.jpg",
            "sname": "商品21",
            "des": "商品描述",
            "price": "￥49"
        },
        {
            "sid": 22,
            "Src": "../img/list/21.jpg",
            "sname": "商品22",
            "des": "商品描述",
            "price": "￥25"
        },
        {
            "sid": 23,
            "Src": "../img/list/22.jpg",
            "sname": "商品23",
            "des": "商品描述",
            "price": "￥67"
        },
        {
            "sid": 24,
            "Src": "../img/list/23.jpg",
            "sname": "商品24",
            "des": "商品描述",
            "price": "￥3"
        },
        {
            "sid": 25,
            "Src": "../img/list/23.jpg",
            "sname": "商品25",
            "des": "商品描述",
            "price": "￥40"
        },
        {
            "sid": 26,
            "Src": "../img/list/25.jpg",
            "sname": "商品26",
            "des": "商品描述",
            "price": "￥68"
        },
        {
            "sid": 27,
            "Src": "../img/list/26.jpg",
            "sname": "商品27",
            "des": "商品描述",
            "price": "￥29.9"
        },
        {
            "sid": 28,
            "Src": "../img/list/27.jpg",
            "sname": "商品28",
            "des": "商品描述",
            "price": "￥18.88"
        }
    ]
}